py3_chanjet/__init__.py
py3_chanjet/u8plus/__init__.py
py3_chanjet/u8plus/pfm/__init__.py
py3_chanjet/u8plus/pfm/zkhb.py
py3_chanjet-1.1.6.dist-info/LICENSE
py3_chanjet-1.1.6.dist-info/METADATA
py3_chanjet-1.1.6.dist-info/WHEEL
py3_chanjet-1.1.6.dist-info/top_level.txt
py3_chanjet-1.1.6.dist-info/RECORD
