Metadata-Version: 2.1
Name: py3-chanjet
Version: 1.1.6
Summary: The Python3 Chanjet Library Developed By Guolei
Home-page: https://github.com/guolei19850528/py3_chanjet
Author: guolei
Author-email: 174000902@qq.com
License: MIT
Requires-Python: >=3.0
License-File: LICENSE
Requires-Dist: py3-requests
Requires-Dist: diskcache
Requires-Dist: redis
Requires-Dist: addict
Requires-Dist: retrying
Requires-Dist: jsonschema
Requires-Dist: xmltodict
Requires-Dist: beautifulsoup4
Requires-Dist: lxml
Requires-Dist: html5lib
Requires-Dist: setuptools
Requires-Dist: wheel
